<?xml version="1.0" encoding="utf-8" ?>
<dwsync>
<file name="index.php" server="ftp-coach-evenements.alwaysdata.net//" local="3676626525" remote="3676619460" Dst="-1" />
<file name="db_connexion.php" server="ftp-coach-evenements.alwaysdata.net//www/" local="132388579430673967" remote="132388507200000000" Dst="2" />
<file name="main.css" server="ftp-coach-evenements.alwaysdata.net//www/" local="132399701514422054" remote="132399629400000000" Dst="2" />
<file name="index.php" server="ftp-coach-evenements.alwaysdata.net//www/" local="132397902713179625" remote="132397830600000000" Dst="2" />
<file name="form.php" server="ftp-coach-evenements.alwaysdata.net//www/" local="132399690471021357" remote="132399618000000000" Dst="2" />
<file name="formProcess.php" server="ftp-coach-evenements.alwaysdata.net//www/" local="132393022690442354" remote="132392950200000000" Dst="2" />
<file name="form2.php" server="ftp-coach-evenements.alwaysdata.net//www/" local="132399671858768391" remote="132399599400000000" Dst="2" />
<file name="delAccount.php" server="ftp-coach-evenements.alwaysdata.net//www/" local="132399034813392823" remote="132398962800000000" Dst="2" />
<file name="delProcess.php" server="ftp-coach-evenements.alwaysdata.net//www/" local="132399035130540819" remote="132398962800000000" Dst="2" />
<file name="form2Process.php" server="ftp-coach-evenements.alwaysdata.net//www/" local="132391266336312068" remote="132391194000000000" Dst="2" />
<file name="form3.php" server="ftp-coach-evenements.alwaysdata.net//www/" local="132399681731363685" remote="132399609600000000" Dst="2" />
<file name="form3Process.php" server="ftp-coach-evenements.alwaysdata.net//www/" local="132394751226149264" remote="132394678800000000" Dst="2" />
<file name="sendEmail.php" server="ftp-coach-evenements.alwaysdata.net//www/" local="132399056626948522" remote="132398984400000000" Dst="2" />
<file name="emailsent.php" server="ftp-coach-evenements.alwaysdata.net//www/" local="132399057478140335" remote="132398985000000000" Dst="2" />
<file name="emailsendingProcess.php" server="ftp-coach-evenements.alwaysdata.net//www/" local="132397250402045394" remote="132397178400000000" Dst="2" />
<file name="functions.php" server="ftp-coach-evenements.alwaysdata.net//www/" local="132399832090513458" remote="132399759600000000" Dst="2" />
<file name="updateProfile.php" server="ftp-coach-evenements.alwaysdata.net//www/" local="132399047038275227" remote="132398974800000000" Dst="2" />
<file name="updateProfileProcess.php" server="ftp-coach-evenements.alwaysdata.net//www/" local="132392995841519063" remote="132392923800000000" Dst="2" />
<file name="form4.php" server="ftp-coach-evenements.alwaysdata.net//www/" local="132399827219024391" remote="132399754800000000" Dst="2" />
<file name="form4Process.php" server="ftp-coach-evenements.alwaysdata.net//www/" local="132394632279654576" remote="132394560000000000" Dst="2" />
<file name="form5Process.php" server="ftp-coach-evenements.alwaysdata.net//www/" local="132394482841336294" remote="132394410600000000" Dst="2" />
<file name="form5.php" server="ftp-coach-evenements.alwaysdata.net//www/" local="132399053972403553" remote="132398981400000000" Dst="2" />
<file name="definePrices.php" server="ftp-coach-evenements.alwaysdata.net//www/" local="132399833115014575" remote="132399760800000000" Dst="2" />
<file name="cgu.php" server="ftp-coach-evenements.alwaysdata.net//www/" local="132399702503926465" remote="132399630000000000" Dst="2" />
<file name="test.php" server="ftp-coach-evenements.alwaysdata.net//www/" local="132398933902048969" remote="132398861400000000" Dst="2" />
</dwsync>